[
    {
        "value": "Remote Failed login",
        "name": "Podman-upgraded legacy tag 003",
        "propertyName": "Entity.IsSuspicious",
        "priority": 5,
        "isPotentialCaseName": true,
        "environments": [],
        "type": 3,
        "compareType": 1,
        "id": 5,
        "creationTimeUnixTimeInMs": 1777536047453,
        "modificationTimeUnixTimeInMs": 1777536047453
    },
    {
        "value": " Out of working hours",
        "name": "Podman-upgraded legacy tag 004",
        "propertyName": "Entity.IsArtifact",
        "priority": 1,
        "isPotentialCaseName": true,
        "environments": [],
        "type": 3,
        "compareType": 4,
        "id": 6,
        "creationTimeUnixTimeInMs": 1777536200798,
        "modificationTimeUnixTimeInMs": 1777536200798
    },
    {
        "value": " IRC Connections",
        "name": "#staging-podman-uplegacy 002",
        "propertyName": "Entity.DataAccessScope",
        "priority": 4,
        "isPotentialCaseName": false,
        "environments": [],
        "type": 3,
        "compareType": 0,
        "id": 4,
        "creationTimeUnixTimeInMs": 1777535991971,
        "modificationTimeUnixTimeInMs": 1777535991971
    },
    {
        "value": " Out of working hours",
        "name": "staging tag-up-legacy_#001",
        "propertyName": "Entity.Environment",
        "priority": 4,
        "isPotentialCaseName": true,
        "environments": [],
        "type": 3,
        "compareType": 2,
        "id": 3,
        "creationTimeUnixTimeInMs": 1777535848706,
        "modificationTimeUnixTimeInMs": 1777535848706
    }
]